caisson/__init__.py
caisson/__main__.py
caisson/configuration.py
caisson/constants.py
caisson/decompressors.py
caisson/io.py
caisson/parser.py
caisson-0.0.4.dist-info/LICENSE
caisson-0.0.4.dist-info/METADATA
caisson-0.0.4.dist-info/WHEEL
caisson-0.0.4.dist-info/entry_points.txt
caisson-0.0.4.dist-info/top_level.txt
caisson-0.0.4.dist-info/zip-safe
caisson-0.0.4.dist-info/RECORD
