Metadata-Version: 2.1
Name: caisson
Version: 0.0.4
Summary: Recursively decompress files
Home-page: https://github.com/nilp0inter/caisson
Author: Roberto Abdelkader Martínez Pérez
Author-email: UNKNOWN
License: GPL2
Keywords: compress,decompress,unzip,7z,unrar
Platform: UNKNOWN
